polars_geodesic_distance-0.2.0.dist-info/METADATA
polars_geodesic_distance-0.2.0.dist-info/WHEEL
polars_geodesic_distance/_internal.pyi
polars_geodesic_distance/typing.py
polars_geodesic_distance/__init__.py
polars_geodesic_distance/_internal.abi3.so
polars_geodesic_distance-0.2.0.dist-info/RECORD
