Metadata-Version: 2.4
Name: polars-geodesic-distance
Version: 0.2.0
Classifier: Programming Language :: Rust
Classifier: Programming Language :: Python :: Implementation :: CPython
Classifier: Programming Language :: Python :: Implementation :: PyPy
Requires-Dist: maturin >=1.8.1
Requires-Dist: pip >=24.3.1
Requires-Dist: polars >=1.8.2
Requires-Dist: pytest >=8.3.4
Requires-Python: >=3.8
